jack_silence_detector/SilenceDetector.py
jack_silence_detector/__init__.py
jack_silence_detector/_version.py
jack_silence_detector/main.py
jack_silence_detector-0.0.3.dist-info/licenses/LICENSE
jack_silence_detector-0.0.3.dist-info/METADATA
jack_silence_detector-0.0.3.dist-info/WHEEL
jack_silence_detector-0.0.3.dist-info/entry_points.txt
jack_silence_detector-0.0.3.dist-info/top_level.txt
jack_silence_detector-0.0.3.dist-info/RECORD
