Metadata-Version: 2.4
Name: jack_silence_detector
Version: 0.0.3
Summary: check when jack clients go silent for a while
Author-email: Max Weidauer <weidauer@campus.tu-berlin.de>
License:                     GNU GENERAL PUBLIC LICENSE
Project-URL: Github, https://github.com/tu-studio/jack-silence-detector
Project-URL: Issues, https://github.com/tu-studio/jack-silence-detector/issues
Requires-Python: >=3.10
License-File: LICENSE
Requires-Dist: JACK-Client
Requires-Dist: click
Requires-Dist: numpy
Dynamic: license-file
